open_mafia_engine/api/__init__.py
open_mafia_engine/builders/all.py
open_mafia_engine/builders/for_testing.py
open_mafia_engine/built_in/all.py
open_mafia_engine/built_in/auxiliary.py
open_mafia_engine/built_in/constraints.py
open_mafia_engine/built_in/information.py
open_mafia_engine/built_in/kills.py
open_mafia_engine/built_in/lynch_tally.py
open_mafia_engine/built_in/notify.py
open_mafia_engine/built_in/outcome.py
open_mafia_engine/built_in/phases.py
open_mafia_engine/built_in/protect.py
open_mafia_engine/built_in/redirect.py
open_mafia_engine/built_in/roleblock.py
open_mafia_engine/built_in/startup.py
open_mafia_engine/built_in/triggers.py
open_mafia_engine/built_in/voting.py
open_mafia_engine/commands/all.py
open_mafia_engine/commands/cli_lexer.py
open_mafia_engine/commands/lobby.py
open_mafia_engine/commands/parser.py
open_mafia_engine/commands/raw.py
open_mafia_engine/commands/runner.py
open_mafia_engine/core/all.py
open_mafia_engine/core/auxiliary.py
open_mafia_engine/core/builder.py
open_mafia_engine/core/converters.py
open_mafia_engine/core/ender.py
open_mafia_engine/core/enums.py
open_mafia_engine/core/event_system.py
open_mafia_engine/core/game.py
open_mafia_engine/core/game_object.py
open_mafia_engine/core/naming.py
open_mafia_engine/core/outcome.py
open_mafia_engine/core/phase_cycle.py
open_mafia_engine/core/state.py
open_mafia_engine/errors.py
open_mafia_engine/examples/cli.py
open_mafia_engine/test/test_ability.py
open_mafia_engine/test/test_build.py
open_mafia_engine/test/test_converters.py
open_mafia_engine/test/test_event.py
open_mafia_engine/test/test_matcher.py
open_mafia_engine/test/test_scenarios.py
open_mafia_engine/util/classes.py
open_mafia_engine/util/enums.py
open_mafia_engine/util/matcher.py
open_mafia_engine/util/namedlist.py
open_mafia_engine/util/repr.py
open_mafia_engine/version.py
open_mafia_engine-0.5.0.dist-info/entry_points.txt
open_mafia_engine-0.5.0.dist-info/LICENSE
open_mafia_engine-0.5.0.dist-info/WHEEL
open_mafia_engine-0.5.0.dist-info/METADATA
open_mafia_engine-0.5.0.dist-info/RECORD
