Metadata-Version: 2.1
Name: open-mafia-engine
Version: 0.5.0
Summary: Open Mafia Engine - a framework for mafia/werewolf games.
Home-page: https://open-mafia-engine.readthedocs.io/en/latest/
License: Apache-2.0
Keywords: mafia,werewolf
Author: Open Mafia Team
Author-email: openmafiateam@gmail.com
Requires-Python: >=3.8,<4.0
Classifier: Development Status :: 3 - Alpha
Classifier: Intended Audience :: Developers
Classifier: License :: OSI Approved :: Apache Software License
Classifier: Operating System :: OS Independent
Classifier: Programming Language :: Python :: 3
Classifier: Programming Language :: Python :: 3.8
Classifier: Programming Language :: Python :: 3.9
Classifier: Topic :: Games/Entertainment :: Board Games
Classifier: Topic :: Games/Entertainment :: Role-Playing
Provides-Extra: dev
Provides-Extra: docs
Provides-Extra: examples
Provides-Extra: recommended
Provides-Extra: test
Requires-Dist: cloudpickle (>=1.6.0,<2.0.0)
Requires-Dist: flake8 (>=3.9.2,<4.0.0); extra == "dev"
Requires-Dist: fuzzywuzzy (>=0.18.0,<0.19.0)
Requires-Dist: makefun (>=1.11.3,<2.0.0)
Requires-Dist: mkdocs (>=1.1.2,<2.0.0); extra == "docs"
Requires-Dist: mkdocs-material (>=7.1.8,<8.0.0); extra == "docs"
Requires-Dist: mkdocstrings (>=0.15.2,<0.16.0); extra == "docs"
Requires-Dist: mypy (>=0.800,<0.801); extra == "dev"
Requires-Dist: prompt-toolkit (>=3.0.19,<4.0.0); extra == "recommended" or extra == "examples"
Requires-Dist: pygments (>=2.9.0,<2.10.0); extra == "recommended" or extra == "docs" or extra == "examples"
Requires-Dist: pymdown-extensions (>=8.2,<9.0); extra == "docs"
Requires-Dist: pytest (>=6.2.4,<7.0.0); extra == "recommended" or extra == "dev" or extra == "test"
Requires-Dist: sortedcontainers (>=2.3.0,<3.0.0)
Requires-Dist: typer (>=0.3.2,<0.4.0)
Project-URL: Documentation, https://open-mafia-engine.readthedocs.io/en/latest/
Project-URL: Repository, https://github.com/open-mafia/open_mafia_engine
